setup.py
PublicLibrary/PublicLibrary.py
PublicLibrary/RobotExtend.py
PublicLibrary/__init__.py
PublicLibrary/version.py
xwfintech_robotframework_common.egg-info/PKG-INFO
xwfintech_robotframework_common.egg-info/SOURCES.txt
xwfintech_robotframework_common.egg-info/dependency_links.txt
xwfintech_robotframework_common.egg-info/not-zip-safe
xwfintech_robotframework_common.egg-info/top_level.txt